Metadata-Version: 2.1
Name: PC-Info
Version: 1.0.2
Summary: PC-Info is a library used for getting all kinds of information about the computer you are using this module on.
Home-page: https://github.com/stop-bark/PC-Info
Author: imagine#0403
Author-email: imagine@stop-bark.club
License: MIT
Keywords: pc-info,info,pc,pcinfo
Platform: UNKNOWN
Classifier: Development Status :: 5 - Production/Stable
Classifier: Intended Audience :: Education
Classifier: Operating System :: Microsoft :: Windows :: Windows 10
Classifier: License :: OSI Approved :: MIT License
Classifier: Programming Language :: Python
Classifier: Programming Language :: Python :: 3.7
Classifier: Programming Language :: Python :: 3.8
Classifier: Programming Language :: Python :: 3.9
